dicfg/__init__.py
dicfg/_version.py
dicfg/config.py
dicfg/factory.py
dicfg/formats.py
dicfg/magics.py
dicfg/reader.py
dicfg/addons/__init__.py
dicfg/addons/addon.py
dicfg/addons/load.py
dicfg/addons/templates.py
dicfg/addons/updaters.py
dicfg/addons/validators.py
dicfg-0.0.18.dist-info/LICENSE
dicfg-0.0.18.dist-info/METADATA
dicfg-0.0.18.dist-info/WHEEL
dicfg-0.0.18.dist-info/top_level.txt
dicfg-0.0.18.dist-info/RECORD
