Metadata-Version: 2.2
Name: dicfg
Version: 0.0.18
Author-email: Mart van Rijthoven <mart.vanrijthoven@gmail.com>
License: MIT License
Project-URL: Homepage, https://github.com/martvanrijthoven/dicfg/
Classifier: Programming Language :: Python :: 3
Classifier: Programming Language :: Python :: 3.9
Classifier: Programming Language :: Python :: 3.10
Classifier: Programming Language :: Python :: 3.11
Classifier: Programming Language :: Python :: 3.12
Classifier: Programming Language :: Python :: 3 :: Only
Classifier: License :: OSI Approved :: MIT License
Classifier: Operating System :: OS Independent
Classifier: Development Status :: 4 - Beta
Requires-Python: >=3.9
License-File: LICENSE
Requires-Dist: PyYaml>=5.4.1
